{
  "resourceType": "StructureDefinition",
  "id": "ext-R5-ImplementationGuide.def.pag.source",
  "extension": [
    {
      "url": "http://hl7.org/fhir/StructureDefinition/structuredefinition-wg",
      "valueCode": "fhir"
    },
    {
      "extension": [
        {
          "url": "packageId",
          "valueId": "hl7.fhir.uv.xver-r5.r4"
        },
        {
          "url": "version",
          "valueString": "0.1.1"
        },
        {
          "url": "uri",
          "valueUri": "http://hl7.org/fhir/uv/xver/ImplementationGuide/hl7.fhir.uv.xver-r5.r4"
        }
      ],
      "url": "http://hl7.org/fhir/StructureDefinition/package-source"
    },
    {
      "extension": [
        {
          "url": "startFhirVersion",
          "valueCode": "4.0"
        },
        {
          "url": "endFhirVersion",
          "valueCode": "4.0"
        }
      ],
      "url": "http://hl7.org/fhir/StructureDefinition/version-specific-use"
    }
  ],
  "url": "http://hl7.org/fhir/5.0/StructureDefinition/extension-ImplementationGuide.definition.page.source",
  "version": "0.1.1",
  "name": "ExtensionImplementationGuide_Definition_Page_Source",
  "title": "R5: Source for page (new)",
  "status": "active",
  "experimental": false,
  "date": "2026-06-12T21:41:14.2230772+00:00",
  "publisher": "FHIR Infrastructure",
  "contact": [
    {
      "name": "FHIR Infrastructure",
      "telecom": [
        {
          "system": "url",
          "value": "http://www.hl7.org/Special/committees/fiwg"
        }
      ]
    }
  ],
  "description": "R5: `ImplementationGuide.definition.page.source[x]` (new:markdown, string, url)",
  "purpose": "This extension is part of the cross-version definitions generated to enable use of the\r\nelement `ImplementationGuide.definition.page.source[x]` as defined in FHIR R5\r\nin FHIR R4.\r\n\r\nThe source element is defined as:\r\n`ImplementationGuide.definition.page.source[x]` 0..1 `markdown, string, url`\r\n\r\nAcross FHIR versions, the element set has been mapped as:\r\n*  R5: `ImplementationGuide.definition.page.source[x]` 0..1 `markdown, string, url`\r\n\r\nFollowing are the generation technical comments:\r\nElement `ImplementationGuide.definition.page.source[x]` has a context of ImplementationGuide.definition.page based on following the parent source element upwards and mapping to `ImplementationGuide`.\nElement `ImplementationGuide.definition.page.source[x]` has no mapping targets in FHIR R4. Typically, this is because the element has been added (is a new element).",
  "fhirVersion": "4.0.1",
  "kind": "complex-type",
  "abstract": false,
  "context": [
    {
      "type": "element",
      "expression": "ImplementationGuide.definition.page"
    }
  ],
  "type": "Extension",
  "baseDefinition": "http://hl7.org/fhir/StructureDefinition/Extension",
  "derivation": "constraint",
  "differential": {
    "element": [
      {
        "id": "Extension",
        "path": "Extension",
        "short": "R5: Source for page (new)",
        "definition": "R5: `ImplementationGuide.definition.page.source[x]` (new:markdown, string, url)",
        "comment": "Element `ImplementationGuide.definition.page.source[x]` has a context of ImplementationGuide.definition.page based on following the parent source element upwards and mapping to `ImplementationGuide`.\nElement `ImplementationGuide.definition.page.source[x]` has no mapping targets in FHIR R4. Typically, this is because the element has been added (is a new element).\nIf absent and the page isn't a generated page, this may be inferred from the page name by checking input locations.  String is used for XHTML content - sent as an escaped string.  FHIR tooling can't support 'direct' XHTML anywhere other than in narrative.",
        "min": 0,
        "max": "1",
        "base": {
          "path": "Extension",
          "min": 0,
          "max": "*"
        },
        "isModifier": false
      },
      {
        "id": "Extension.url",
        "path": "Extension.url",
        "min": 1,
        "max": "1",
        "base": {
          "path": "Extension.url",
          "min": 1,
          "max": "1"
        },
        "fixedUri": "http://hl7.org/fhir/5.0/StructureDefinition/extension-ImplementationGuide.definition.page.source"
      },
      {
        "id": "Extension.value[x]",
        "path": "Extension.value[x]",
        "short": "Source for page",
        "definition": "Indicates the URL or the actual content to provide for the page.",
        "comment": "If absent and the page isn't a generated page, this may be inferred from the page name by checking input locations.  String is used for XHTML content - sent as an escaped string.  FHIR tooling can't support 'direct' XHTML anywhere other than in narrative.",
        "min": 0,
        "max": "1",
        "base": {
          "path": "Extension.value[x]",
          "min": 0,
          "max": "1"
        },
        "type": [
          {
            "code": "url"
          },
          {
            "code": "string"
          },
          {
            "code": "markdown"
          }
        ]
      }
    ]
  }
}