{
  "resourceType": "ValueSet",
  "id": "R5-v2-0255-for-R4",
  "extension": [
    {
      "url": "http://hl7.org/fhir/StructureDefinition/structuredefinition-wg",
      "valueCode": "fhir"
    },
    {
      "extension": [
        {
          "url": "packageId",
          "valueId": "hl7.fhir.uv.xver-r5.r4"
        },
        {
          "url": "version",
          "valueString": "0.1.1"
        },
        {
          "url": "uri",
          "valueUri": "http://hl7.org/fhir/uv/xver/ImplementationGuide/hl7.fhir.uv.xver-r5.r4"
        }
      ],
      "url": "http://hl7.org/fhir/StructureDefinition/package-source"
    }
  ],
  "url": "http://hl7.org/fhir/uv/xver/ValueSet/R5-v2-0255-for-R4",
  "version": "0.1.1",
  "name": "R5V20255ForR4",
  "title": "Cross-version ValueSet R5.Hl7VSDurationCategories for use in FHIR R4",
  "status": "active",
  "experimental": false,
  "date": "2026-06-12T21:41:14.2230772+00:00",
  "publisher": "FHIR Infrastructure",
  "contact": [
    {
      "name": "FHIR Infrastructure",
      "telecom": [
        {
          "system": "url",
          "value": "http://www.hl7.org/Special/committees/fiwg"
        }
      ]
    }
  ],
  "description": "This cross-version ValueSet represents content from `http://terminology.hl7.org/ValueSet/v2-0255|2.0.0` for use in FHIR R4.",
  "purpose": "This value set is part of the cross-version definitions generated to enable use of the\r\nvalue set `http://terminology.hl7.org/ValueSet/v2-0255|2.0.0` as defined in FHIR R5\r\nin FHIR R4.\r\n\r\nThe source value set is bound to the following FHIR R5 elements:\r\n* \r\n\r\nNote that all concepts are included in this cross-version definition because no concepts have compatible representations\r\n\r\nFollowing are the generation technical comments:\r\n\nFHIR ValueSet `http://terminology.hl7.org/ValueSet/v2-0255|2.0.0`, defined in FHIR R5 does not have any mapping to FHIR R4",
  "compose": {
    "include": [
      {
        "system": "http://terminology.hl7.org/CodeSystem/v2-0255",
        "version": "2.3.0",
        "concept": [
          {
            "code": "*",
            "display": "(asterisk) Life of the \"unit\""
          },
          {
            "code": "12H",
            "display": "12 hours"
          },
          {
            "code": "1H",
            "display": "1 hour"
          },
          {
            "code": "1L",
            "display": "1 months (30 days)"
          },
          {
            "code": "1W",
            "display": "1 week"
          },
          {
            "code": "2.5H",
            "display": "2 1/2 hours"
          },
          {
            "code": "24H",
            "display": "24 hours"
          },
          {
            "code": "2D",
            "display": "2 days"
          },
          {
            "code": "2H",
            "display": "2 hours"
          },
          {
            "code": "2L",
            "display": "2 months"
          },
          {
            "code": "2W",
            "display": "2 weeks"
          },
          {
            "code": "30M",
            "display": "30 minutes"
          },
          {
            "code": "3D",
            "display": "3 days"
          },
          {
            "code": "3H",
            "display": "3 hours"
          },
          {
            "code": "3L",
            "display": "3 months"
          },
          {
            "code": "3W",
            "display": "3 weeks"
          },
          {
            "code": "4D",
            "display": "4 days"
          },
          {
            "code": "4H",
            "display": "4 hours"
          },
          {
            "code": "4W",
            "display": "4 weeks"
          },
          {
            "code": "5D",
            "display": "5 days"
          },
          {
            "code": "5H",
            "display": "5 hours"
          },
          {
            "code": "6D",
            "display": "6 days"
          },
          {
            "code": "6H",
            "display": "6 hours"
          },
          {
            "code": "7H",
            "display": "7 hours"
          },
          {
            "code": "8H",
            "display": "8 hours"
          },
          {
            "code": "LU",
            "display": "Life of the \"unit\""
          },
          {
            "code": "PT",
            "display": "point in time"
          }
        ]
      }
    ]
  },
  "expansion": {
    "timestamp": "2026-06-12T21:41:14.2230772+00:00",
    "contains": [
      {
        "system": "http://terminology.hl7.org/CodeSystem/v2-0255",
        "version": "2.3.0",
        "code": "*",
        "display": "(asterisk) Life of the \"unit\""
      },
      {
        "system": "http://terminology.hl7.org/CodeSystem/v2-0255",
        "version": "2.3.0",
        "code": "12H",
        "display": "12 hours"
      },
      {
        "system": "http://terminology.hl7.org/CodeSystem/v2-0255",
        "version": "2.3.0",
        "code": "1H",
        "display": "1 hour"
      },
      {
        "system": "http://terminology.hl7.org/CodeSystem/v2-0255",
        "version": "2.3.0",
        "code": "1L",
        "display": "1 months (30 days)"
      },
      {
        "system": "http://terminology.hl7.org/CodeSystem/v2-0255",
        "version": "2.3.0",
        "code": "1W",
        "display": "1 week"
      },
      {
        "system": "http://terminology.hl7.org/CodeSystem/v2-0255",
        "version": "2.3.0",
        "code": "2.5H",
        "display": "2 1/2 hours"
      },
      {
        "system": "http://terminology.hl7.org/CodeSystem/v2-0255",
        "version": "2.3.0",
        "code": "24H",
        "display": "24 hours"
      },
      {
        "system": "http://terminology.hl7.org/CodeSystem/v2-0255",
        "version": "2.3.0",
        "code": "2D",
        "display": "2 days"
      },
      {
        "system": "http://terminology.hl7.org/CodeSystem/v2-0255",
        "version": "2.3.0",
        "code": "2H",
        "display": "2 hours"
      },
      {
        "system": "http://terminology.hl7.org/CodeSystem/v2-0255",
        "version": "2.3.0",
        "code": "2L",
        "display": "2 months"
      },
      {
        "system": "http://terminology.hl7.org/CodeSystem/v2-0255",
        "version": "2.3.0",
        "code": "2W",
        "display": "2 weeks"
      },
      {
        "system": "http://terminology.hl7.org/CodeSystem/v2-0255",
        "version": "2.3.0",
        "code": "30M",
        "display": "30 minutes"
      },
      {
        "system": "http://terminology.hl7.org/CodeSystem/v2-0255",
        "version": "2.3.0",
        "code": "3D",
        "display": "3 days"
      },
      {
        "system": "http://terminology.hl7.org/CodeSystem/v2-0255",
        "version": "2.3.0",
        "code": "3H",
        "display": "3 hours"
      },
      {
        "system": "http://terminology.hl7.org/CodeSystem/v2-0255",
        "version": "2.3.0",
        "code": "3L",
        "display": "3 months"
      },
      {
        "system": "http://terminology.hl7.org/CodeSystem/v2-0255",
        "version": "2.3.0",
        "code": "3W",
        "display": "3 weeks"
      },
      {
        "system": "http://terminology.hl7.org/CodeSystem/v2-0255",
        "version": "2.3.0",
        "code": "4D",
        "display": "4 days"
      },
      {
        "system": "http://terminology.hl7.org/CodeSystem/v2-0255",
        "version": "2.3.0",
        "code": "4H",
        "display": "4 hours"
      },
      {
        "system": "http://terminology.hl7.org/CodeSystem/v2-0255",
        "version": "2.3.0",
        "code": "4W",
        "display": "4 weeks"
      },
      {
        "system": "http://terminology.hl7.org/CodeSystem/v2-0255",
        "version": "2.3.0",
        "code": "5D",
        "display": "5 days"
      },
      {
        "system": "http://terminology.hl7.org/CodeSystem/v2-0255",
        "version": "2.3.0",
        "code": "5H",
        "display": "5 hours"
      },
      {
        "system": "http://terminology.hl7.org/CodeSystem/v2-0255",
        "version": "2.3.0",
        "code": "6D",
        "display": "6 days"
      },
      {
        "system": "http://terminology.hl7.org/CodeSystem/v2-0255",
        "version": "2.3.0",
        "code": "6H",
        "display": "6 hours"
      },
      {
        "system": "http://terminology.hl7.org/CodeSystem/v2-0255",
        "version": "2.3.0",
        "code": "7H",
        "display": "7 hours"
      },
      {
        "system": "http://terminology.hl7.org/CodeSystem/v2-0255",
        "version": "2.3.0",
        "code": "8H",
        "display": "8 hours"
      },
      {
        "system": "http://terminology.hl7.org/CodeSystem/v2-0255",
        "version": "2.3.0",
        "code": "LU",
        "display": "Life of the \"unit\""
      },
      {
        "system": "http://terminology.hl7.org/CodeSystem/v2-0255",
        "version": "2.3.0",
        "code": "PT",
        "display": "point in time"
      }
    ]
  }
}